simpleparam/__init__.py
simpleparam/store.py
simpleparam/utilities.py
simpleparam-0.0.1.dist-info/LICENSE
simpleparam-0.0.1.dist-info/METADATA
simpleparam-0.0.1.dist-info/WHEEL
simpleparam-0.0.1.dist-info/top_level.txt
simpleparam-0.0.1.dist-info/RECORD
