Metadata-Version: 2.1
Name: simpleparam
Version: 0.0.1
Summary: SimpleParam: simplified parameters with optional type and range checking
Home-page: https://github.com/lukasz-migas/SimpleParam
Author: Lukasz G. Migas
Author-email: lukas.migas@yahoo.com
Maintainer: Lukasz G. Migas
Maintainer-email: lukas.migas@yahoo.com
License: Apache license 2.0
Download-URL: https://github.com/lukasz-migas/SimpleParam
Platform: UNKNOWN
Classifier: Intended Audience :: Science/Research
Classifier: Programming Language :: Python :: 3.5
Classifier: Programming Language :: Python :: 3.6
Classifier: Programming Language :: Python :: 3.7
Classifier: Programming Language :: Python :: 3.8
Classifier: Operating System :: POSIX
Classifier: Operating System :: Unix
Classifier: Operating System :: MacOS
Classifier: Operating System :: Microsoft :: Windows
Classifier: Natural Language :: English
